aduubao_adb/__init__.py
aduubao_adb-0.1.dist-info/METADATA
aduubao_adb-0.1.dist-info/WHEEL
aduubao_adb-0.1.dist-info/top_level.txt
aduubao_adb-0.1.dist-info/RECORD
