Metadata-Version: 2.1
Name: aduubao-adb
Version: 0.1
Summary: Biblioteca Aduubao ADB para áudio, texto, janelas e arquivos
Home-page: UNKNOWN
Author: Arthur (Aduubao)
Author-email: seu_email@exemplo.com
License: UNKNOWN
Platform: UNKNOWN
Classifier: Programming Language :: Python :: 3
